<?xml version="1.0"?>
<effect><History><PreviousPath>s:\complete\effects\effects\shootgun1\shootgun1.eff</PreviousPath><PreviousDate>21.10.2002</PreviousDate><PreviousTime>14:16:00</PreviousTime><PreviousOwner>Alexey.Serkov</PreviousOwner><Action>Exported as</Action><CurrentPath>s:\versions\current\data\effects\effects\shootgun1.xml</CurrentPath><CurrentDate>21.10.2002</CurrentDate><CurrentTime>14:16:04</CurrentTime><CurrentOwner>Alexey.Serkov</CurrentOwner></History><effect><sprites/><particles><item start="25" duration="3500" scale="0.5"><path>Effects\particles\aa_flame1_of_shootgun</path><pos x="0" y="0" z="0"/></item><item start="0" duration="15320" scale="0.2"><path>Effects\particles\aa_sparkles1_of_directhit</path><pos x="0" y="0" z="0"/></item></particles><SmokinParticles/><sound>Cannon_shot1</sound></effect></effect>
