<?xml version="1.0"?>
<effect><History><PreviousPath>s:\complete\effects\effects\smoketrain1\current.eff</PreviousPath><PreviousDate>21.10.2002</PreviousDate><PreviousTime>16:48:34</PreviousTime><PreviousOwner>Alexey.Serkov</PreviousOwner><Action>Exported as</Action><CurrentPath>s:\versions\current\data\effects\effects\smoketrain.xml</CurrentPath><CurrentDate>21.10.2002</CurrentDate><CurrentTime>16:48:37</CurrentTime><CurrentOwner>Alexey.Serkov</CurrentOwner></History><effect><sprites/><particles><item start="0" duration="15003000" scale="0.3"><path>Effects\particles\aa_smoke1_of_train</path><pos x="0" y="0" z="0"/></item></particles><SmokinParticles/><sound></sound></effect></effect>
