<?xml version="1.0"?>
<base><History><PreviousPath>s:\complete\objects\Europe\Summer\E_DirectionSignWood\04\current.obt</PreviousPath><PreviousDate>20.09.2002</PreviousDate><PreviousTime>18:22:43</PreviousTime><PreviousOwner></PreviousOwner><Action>Batch exported as</Action><CurrentPath>s:\versions\current\data\objects\europe\summer\e_directionsignwood\04\1.xml</CurrentPath><CurrentDate>20.09.2002</CurrentDate><CurrentTime>18:29:48</CurrentTime><CurrentOwner>Alexander.Valencia</CurrentOwner></History><desc MaxHP="15" RepairCost="1" AIClasses="0" Burn="0"><KeyName></KeyName><StatsType>ObjDesc</StatsType><DamagedHPs/><Defence0 MinArmor="9" MaxArmor="9" Silhouette="1"/><Defence1 MinArmor="9" MaxArmor="9" Silhouette="1"/><Defence2 MinArmor="9" MaxArmor="9" Silhouette="1"/><Defence3 MinArmor="9" MaxArmor="9" Silhouette="1"/><Defence4 MinArmor="9" MaxArmor="9" Silhouette="1"/><Defence5 MinArmor="9" MaxArmor="9" Silhouette="1"/><EffectExplosion>expobj1</EffectExplosion><EffectDeath></EffectDeath><passability><item size_x="1" size_y="1"/><item>01</item></passability><origin x="14.9907" y="5.37354"/><VisOrigin x="14.9907" y="5.37354"/><visibility><item size_x="1" size_y="1"/><item>07</item></visibility><CycledSound></CycledSound><AmbientSound></AmbientSound></desc></base>
