<?xml version="1.0"?>
<!-- deleted comment here -->
<!-- deleted comment here -->
<base>
	<RPG>
		<KeyName>german auto (tracks unitts) ack set 1</KeyName>
		<StatsType>Ack</StatsType>
		<Types>
			<item Type="0">
				<Acks>
					<item Probability="14">
						<Sound>ack_german_truck1-1-1</Sound>
					</item>
					<item Probability="14">
						<Sound>ack_german_truck1-1-2</Sound>
					</item>
					<item Probability="14">
						<Sound>ack_german_truck1-1-3</Sound>
					</item>
					<item Probability="14">
						<Sound>ack_german_truck1-1-4</Sound>
					</item>
					<item Probability="14">
						<Sound>ack_german_truck1-1-5</Sound>
					</item>
					<item Probability="14">
						<Sound>ack_german_truck1-1-6</Sound>
					</item>
					<item Probability="14">
						<Sound>ack_german_truck1-1-7</Sound>
					</item>
				</Acks>
			</item>
			<item Type="1">
				<Acks>
					<item Probability="20">
						<Sound>ack_german_truck1-2-1</Sound>
					</item>
					<item Probability="20">
						<Sound>ack_german_truck1-2-2</Sound>
					</item>
					<item Probability="20">
						<Sound>ack_german_truck1-2-3</Sound>
					</item>
					<item Probability="20">
						<Sound>ack_german_truck1-2-4</Sound>
					</item>
					<item Probability="20">
						<Sound>ack_german_truck1-2-5</Sound>
					</item>
				</Acks>
			</item>
			<item Type="2">
				<Acks>
					<item Probability="20">
						<Sound>ack_german_truck1-3-1</Sound>
					</item>
					<item Probability="20">
						<Sound>ack_german_truck1-3-2</Sound>
					</item>
					<item Probability="20">
						<Sound>ack_german_truck1-3-3</Sound>
					</item>
					<item Probability="20">
						<Sound>ack_german_truck1-3-4</Sound>
					</item>
					<item Probability="20">
						<Sound>ack_german_truck1-3-5</Sound>
					</item>
				</Acks>
			</item>
			<item Type="12">
				<Acks>
					<item Probability="33">
						<Sound>ack_german_truck1-9-1</Sound>
					</item>
					<item Probability="33">
						<Sound>ack_german_truck1-9-2</Sound>
					</item>
					<item Probability="33">
						<Sound>ack_german_truck1-9-3</Sound>
					</item>
				</Acks>
			</item>
			<item Type="15">
				<Acks>
					<item Probability="14">
						<Sound>ack_german_truck1-10-1</Sound>
					</item>
					<item Probability="14">
						<Sound>ack_german_truck1-10-2</Sound>
					</item>
					<item Probability="14">
						<Sound>ack_german_truck1-10-3</Sound>
					</item>
					<item Probability="14">
						<Sound>ack_german_truck1-10-4</Sound>
					</item>
					<item Probability="14">
						<Sound>ack_german_truck1-10-5</Sound>
					</item>
					<item Probability="14">
						<Sound>ack_german_truck1-10-6</Sound>
					</item>
					<item Probability="14">
						<Sound>ack_german_truck1-10-7</Sound>
					</item>
				</Acks>
			</item>
			<item Type="16">
				<Acks>
					<item Probability="33">
						<Sound>ack_german_truck1-11-1</Sound>
					</item>
					<item Probability="33">
						<Sound>ack_german_truck1-11-2</Sound>
					</item>
					<item Probability="33">
						<Sound>ack_german_truck1-11-3</Sound>
					</item>
				</Acks>
			</item>
			<item Type="17">
				<Acks>
					<item Probability="33">
						<Sound>ack_german_truck1-12-1</Sound>
					</item>
					<item Probability="33">
						<Sound>ack_german_truck1-12-2</Sound>
					</item>
					<item Probability="33">
						<Sound>ack_german_truck1-12-3</Sound>
					</item>
				</Acks>
			</item>
			<item Type="18">
				<Acks>
					<item Probability="33">
						<Sound>ack_german_truck1-13-1</Sound>
					</item>
					<item Probability="33">
						<Sound>ack_german_truck1-13-2</Sound>
					</item>
					<item Probability="33">
						<Sound>ack_german_truck1-13-3</Sound>
					</item>
				</Acks>
			</item>
			<item Type="19">
				<Acks>
					<item Probability="33">
						<Sound>ack_german_truck1-14-1</Sound>
					</item>
					<item Probability="33">
						<Sound>ack_german_truck1-14-2</Sound>
					</item>
					<item Probability="33">
						<Sound>ack_german_truck1-14-3</Sound>
					</item>
				</Acks>
			</item>
			<item Type="20">
				<Acks>
					<item Probability="50">
						<Sound>ack_german_truck1-15-1</Sound>
					</item>
					<item Probability="50">
						<Sound>ack_german_truck1-15-2</Sound>
					</item>
				</Acks>
			</item>
			<item Type="21">
				<Acks>
					<item Probability="33">
						<Sound>ack_german_truck1-16-1</Sound>
					</item>
					<item Probability="33">
						<Sound>ack_german_truck1-16-2</Sound>
					</item>
					<item Probability="33">
						<Sound>ack_german_truck1-16-3</Sound>
					</item>
				</Acks>
			</item>
			<item Type="22">
				<Acks>
					<item Probability="33">
						<Sound>ack_german_truck1-17-1</Sound>
					</item>
					<item Probability="33">
						<Sound>ack_german_truck1-17-2</Sound>
					</item>
					<item Probability="33">
						<Sound>ack_german_truck1-17-3</Sound>
					</item>
				</Acks>
			</item>
			<item Type="27">
				<Acks>
					<item Probability="25">
						<Sound>ack_german_truck1-18-1</Sound>
					</item>
					<item Probability="25">
						<Sound>ack_german_truck1-18-2</Sound>
					</item>
					<item Probability="25">
						<Sound>ack_german_truck1-18-3</Sound>
					</item>
					<item Probability="25">
						<Sound>ack_german_truck1-18-4</Sound>
					</item>
				</Acks>
			</item>
			<item Type="29">
				<Acks>
					<item Probability="50">
						<Sound>ack_german_truck1-19-1</Sound>
					</item>
					<item Probability="50">
						<Sound>ack_german_truck1-19-2</Sound>
					</item>
				</Acks>
			</item>
			<item Type="30">
				<Acks>
					<item Probability="50">
						<Sound>ack_german_truck1-20-1</Sound>
					</item>
					<item Probability="50">
						<Sound>ack_german_truck1-20-2</Sound>
					</item>
				</Acks>
			</item>
			<item Type="40">
				<Acks>
					<item Probability="25">
						<Sound>ack_german_truck1-24-1</Sound>
					</item>
					<item Probability="25">
						<Sound>ack_german_truck1-24-2</Sound>
					</item>
					<item Probability="25">
						<Sound>ack_german_truck1-24-3</Sound>
					</item>
					<item Probability="25">
						<Sound>ack_german_truck1-24-4</Sound>
					</item>
				</Acks>
			</item>
			<item Type="42">
				<Acks>
					<item Probability="20">
						<Sound>ack_german_truck1-25-1</Sound>
					</item>
					<item Probability="20">
						<Sound>ack_german_truck1-25-2</Sound>
					</item>
					<item Probability="20">
						<Sound>ack_german_truck1-25-3</Sound>
					</item>
					<item Probability="20">
						<Sound>ack_german_truck1-25-4</Sound>
					</item>
					<item Probability="20">
						<Sound>ack_german_truck1-25-5</Sound>
					</item>
				</Acks>
			</item>
			<item Type="43">
				<Acks>
					<item Probability="25">
						<Sound>ack_german_truck1-26-2</Sound>
					</item>
					<item Probability="25">
						<Sound>ack_german_truck1-26-3</Sound>
					</item>
				</Acks>
			</item>
			<item Type="45">
				<Acks>
					<item Probability="14">
						<Sound>ack_german_truck1-27-1</Sound>
					</item>
					<item Probability="14">
						<Sound>ack_german_truck1-27-2</Sound>
					</item>
					<item Probability="14">
						<Sound>ack_german_truck1-27-3</Sound>
					</item>
					<item Probability="14">
						<Sound>ack_german_truck1-27-4</Sound>
					</item>
					<item Probability="14">
						<Sound>ack_german_truck1-27-5</Sound>
					</item>
					<item Probability="14">
						<Sound>ack_german_truck1-27-6</Sound>
					</item>
					<item Probability="14">
						<Sound>ack_german_truck1-27-7</Sound>
					</item>
				</Acks>
			</item>
			<item Type="48">
				<Acks>
					<item Probability="25">
						<Sound>ack_german_truck1-29-1</Sound>
					</item>
					<item Probability="25">
						<Sound>ack_german_truck1-29-2</Sound>
					</item>
					<item Probability="25">
						<Sound>ack_german_truck1-29-3</Sound>
					</item>
					<item Probability="25">
						<Sound>ack_german_truck1-29-4</Sound>
					</item>
				</Acks>
			</item>
			<item Type="49">
				<Acks>
					<item Probability="50">
						<Sound>ack_german_truck1-30-1</Sound>
					</item>
					<item Probability="50">
						<Sound>ack_german_truck1-30-2</Sound>
					</item>
				</Acks>
			</item>
			<item Type="50">
				<Acks>
					<item Probability="20">
						<Sound>ack_german_truck1-31-1</Sound>
					</item>
					<item Probability="20">
						<Sound>ack_german_truck1-31-2</Sound>
					</item>
					<item Probability="20">
						<Sound>ack_german_truck1-31-3</Sound>
					</item>
					<item Probability="20">
						<Sound>ack_german_truck1-31-4</Sound>
					</item>
					<item Probability="20">
						<Sound>ack_german_truck1-31-5</Sound>
					</item>
				</Acks>
			</item>
			<item Type="53">
				<Acks>
					<item Probability="33">
						<Sound>ack_german_truck1-36-1</Sound>
					</item>
					<item Probability="33">
						<Sound>ack_german_truck1-36-2</Sound>
					</item>
					<item Probability="33">
						<Sound>ack_german_truck1-36-3</Sound>
					</item>
				</Acks>
			</item>
			<item Type="54">
				<Acks>
					<item Probability="33">
						<Sound>ack_german_truck1-37-1</Sound>
					</item>
					<item Probability="33">
						<Sound>ack_german_truck1-37-2</Sound>
					</item>
					<item Probability="33">
						<Sound>ack_german_truck1-37-3</Sound>
					</item>
				</Acks>
			</item>
			<item Type="55">
				<Acks>
					<item Probability="50">
						<Sound>ack_german_truck1-38-1</Sound>
					</item>
					<item Probability="50">
						<Sound>ack_german_truck1-38-2</Sound>
					</item>
				</Acks>
			</item>
		</Types>
	</RPG>
</base>
