<?xml version="1.0"?>
<base><History><PreviousPath>s:\complete\scenarios\missions\ussr\leningrad\scenariomission\current.mip</PreviousPath><PreviousDate>27.09.2002</PreviousDate><PreviousTime>15:59:54</PreviousTime><PreviousOwner>Alexander.Vinnikov</PreviousOwner><Action>Exported as</Action><CurrentPath>c:\a7\data\scenarios\scenariomissions\ussr\leningrad\1.xml</CurrentPath><CurrentDate>27.09.2002</CurrentDate><CurrentTime>15:59:56</CurrentTime><CurrentOwner>Alexander.Vinnikov</CurrentOwner></History><RPG><KeyName></KeyName><StatsType>Mission</StatsType><HeaderText>scenarios\scenariomissions\ussr\leningrad\header</HeaderText><SubheaderText>scenarios\scenariomissions\ussr\leningrad\subheader</SubheaderText><DescriptionText>scenarios\scenariomissions\ussr\leningrad\description</DescriptionText><MapImage>scenarios\scenariomissions\ussr\leningrad\map</MapImage><MapImageRect x1="512" y1="512" x2="1.00098" y2="1.00098"/><TemplateMap></TemplateMap><FinalMap>ussr\leningrad\pskovsolcy</FinalMap><CombatMusics><item>music\combat1</item><item>music\combat2</item><item>music\combat3</item></CombatMusics><ExplorMusics><item>music\explore1</item><item>music\explore2</item><item>music\explore3</item><item>music\explore4</item><item>music\explore_russian</item></ExplorMusics><Objectives><item Secret="0" AnchorScriptID="-1"><Header>scenarios\scenariomissions\ussr\leningrad\0h</Header><DescriptionText>scenarios\scenariomissions\ussr\leningrad\0</DescriptionText><PosOnMap x="344" y="401"/></item><item Secret="1" AnchorScriptID="-1"><Header>scenarios\scenariomissions\ussr\leningrad\1h</Header><DescriptionText>scenarios\scenariomissions\ussr\leningrad\1</DescriptionText><PosOnMap x="316" y="399"/></item><item Secret="0" AnchorScriptID="-1"><Header>scenarios\scenariomissions\ussr\leningrad\2h</Header><DescriptionText>scenarios\scenariomissions\ussr\leningrad\2</DescriptionText><PosOnMap x="125" y="73"/></item><item Secret="1" AnchorScriptID="-1"><Header>scenarios\scenariomissions\ussr\leningrad\3h</Header><DescriptionText>scenarios\scenariomissions\ussr\leningrad\3</DescriptionText><PosOnMap x="225" y="69"/></item><item Secret="1" AnchorScriptID="-1"><Header>scenarios\scenariomissions\ussr\leningrad\4h</Header><DescriptionText>scenarios\scenariomissions\ussr\leningrad\4</DescriptionText><PosOnMap x="126" y="157"/></item><item Secret="0" AnchorScriptID="-1"><Header>scenarios\scenariomissions\ussr\leningrad\5h</Header><DescriptionText>scenarios\scenariomissions\ussr\leningrad\5</DescriptionText><PosOnMap x="129" y="431"/></item><item Secret="0" AnchorScriptID="-1"><Header>scenarios\scenariomissions\ussr\leningrad\6h</Header><DescriptionText>scenarios\scenariomissions\ussr\leningrad\6</DescriptionText><PosOnMap x="111" y="385"/></item></Objectives><SettingName></SettingName></RPG></base>
