<?xml version="1.0"?>
<base><History><PreviousPath>s:\complete\terraobjects\Common\Winter\Ravine\Big\09\current.obt</PreviousPath><PreviousDate>20.02.2002</PreviousDate><PreviousTime>19:08:03</PreviousTime><PreviousOwner></PreviousOwner><Action>Batch exported as</Action><CurrentPath>s:\versions\current\data\terraobjects\common\winter\ravine\big\09\1.xml</CurrentPath><CurrentDate>18.06.2002</CurrentDate><CurrentTime>20:03:24</CurrentTime><CurrentOwner>Yury.Blazhevich</CurrentOwner></History><desc MaxHP="100" RepairCost="1" AIClasses="0" Burn="80"><KeyName></KeyName><StatsType>ObjDesc</StatsType><DamagedHPs/><passability><item size_x="5" size_y="5"/><item>0101010000</item><item>0101010000</item><item>0101010100</item><item>0001010101</item><item>0000010101</item></passability><origin x="62.3674" y="55.5781"/><VisOrigin x="39.7401" y="32.9507"/><visibility><item size_x="3" size_y="4"/><item>282800</item><item>002800</item><item>002828</item><item>000028</item></visibility><EffectExplosion MinDist="1" MaxDist="2"><Effect></Effect><Sound></Sound></EffectExplosion><EffectDeath MinDist="1" MaxDist="2"><Effect></Effect><Sound></Sound></EffectDeath></desc></base>
