<?xml version="1.0"?>
<base><History><PreviousPath>s:\complete\buildings\Europe\Summer\E_House11_1\current.bld</PreviousPath><PreviousDate>23.01.2003</PreviousDate><PreviousTime>12:20:28</PreviousTime><PreviousOwner>elena.Sevostyanova</PreviousOwner><Action>Batch exported as</Action><CurrentPath>s:\versions\current\data\buildings\europe\summer\e_house11_1\1.xml</CurrentPath><CurrentDate>23.01.2003</CurrentDate><CurrentTime>12:29:05</CurrentTime><CurrentOwner>Alexander.Valencia</CurrentOwner></History><desc MaxHP="750" RepairCost="1" AIClasses="0" Burn="0" RestSlots="40" MedicalSlots="5"><KeyName>Unknown Building</KeyName><StatsType>Building</StatsType><DamagedHPs/><Defence0 MinArmor="15" MaxArmor="20" Silhouette="1"/><Defence1 MinArmor="15" MaxArmor="20" Silhouette="1"/><Defence2 MinArmor="15" MaxArmor="20" Silhouette="1"/><Defence3 MinArmor="15" MaxArmor="20" Silhouette="1"/><Defence4 MinArmor="5" MaxArmor="15" Silhouette="1"/><Defence5 MinArmor="5" MaxArmor="15" Silhouette="1"/><EffectExplosion></EffectExplosion><EffectDeath></EffectDeath><passability><item size_x="6" size_y="9"/><item>010101010100</item><item>010101010100</item><item>010101010100</item><item>010101010101</item><item>010101010101</item><item>010101010101</item><item>010101010101</item><item>010101010100</item><item>010101010100</item></passability><origin x="108.329" y="-0.283264"/><VisOrigin x="108.329" y="-0.283264"/><visibility><item size_x="6" size_y="9"/><item>010101010100</item><item>070707070100</item><item>070707070701</item><item>070707070707</item><item>070707070707</item><item>070707070707</item><item>070707070701</item><item>070707070100</item><item>070707010100</item></visibility><CycledSound></CycledSound><AmbientSound></AmbientSound><BuildingType>00000000</BuildingType><FireSlots><item Direction="180" Angle="148.414" SightMultiplier="1" Coverage="1" Ammo="100" GunPriority="1" RotationSpeed="1" BeforeSprite="1" ShowFlashes="0"><Position x="-20.6475" y="0.283264" z="0"/><Weapon></Weapon><PicturePosition x="-14.3995" y="-50.4001"/><WorldPosition x="-21.4955" y="1.13165" z="48.9595"/></item><item Direction="180" Angle="148.414" SightMultiplier="1" Coverage="1" Ammo="100" GunPriority="1" RotationSpeed="1" BeforeSprite="1" ShowFlashes="0"><Position x="-60.2455" y="25.7391" z="0"/><Weapon></Weapon><PicturePosition x="-24.3995" y="-86.4001"/><WorldPosition x="-35.6375" y="1.13153" z="84.7553"/></item><item Direction="180" Angle="148.414" SightMultiplier="1" Coverage="1" Ammo="100" GunPriority="1" RotationSpeed="1" BeforeSprite="1" ShowFlashes="0"><Position x="-77.923" y="30.6889" z="0"/><Weapon></Weapon><PicturePosition x="-33.3997" y="-123.4"/><WorldPosition x="-49.0727" y="1.83844" z="121.706"/></item><item Direction="270" Angle="142.504" SightMultiplier="1" Coverage="1" Ammo="100" GunPriority="1" RotationSpeed="1" BeforeSprite="1" ShowFlashes="0"><Position x="27.4358" y="70.9939" z="0"/><Weapon></Weapon><PicturePosition x="69.6004" y="-40.4001"/><WorldPosition x="19.5165" y="78.9135" z="22.4012"/></item><item Direction="270" Angle="142.504" SightMultiplier="1" Coverage="1" Ammo="100" GunPriority="1" RotationSpeed="1" BeforeSprite="1" ShowFlashes="0"><Position x="-2.96973" y="71.701" z="0"/><Weapon></Weapon><PicturePosition x="48.6005" y="-97.4"/><WorldPosition x="7.49591" y="61.2357" z="90.5286"/></item><item Direction="270" Angle="142.504" SightMultiplier="1" Coverage="1" Ammo="100" GunPriority="1" RotationSpeed="1" BeforeSprite="1" ShowFlashes="0"><Position x="-4.38397" y="107.056" z="0"/><Weapon></Weapon><PicturePosition x="72.6005" y="-110.4"/><WorldPosition x="20.2238" y="82.4489" z="102.076"/></item><item Direction="270" Angle="142.504" SightMultiplier="1" Coverage="1" Ammo="100" GunPriority="1" RotationSpeed="1" BeforeSprite="1" ShowFlashes="0"><Position x="-19.9404" y="193.323" z="0"/><Weapon></Weapon><PicturePosition x="122.6" y="-103.4"/><WorldPosition x="18.8089" y="154.574" z="63.9702"/></item><item Direction="0" Angle="145.435" SightMultiplier="1" Coverage="1" Ammo="100" GunPriority="1" RotationSpeed="1" BeforeSprite="0" ShowFlashes="0"><Position x="-58.8312" y="203.93" z="0"/><Weapon></Weapon><PicturePosition x="102.6" y="-136.4"/><WorldPosition x="20.2234" y="124.875" z="114.777"/></item><item Direction="90" Angle="142.504" SightMultiplier="1" Coverage="1" Ammo="100" GunPriority="1" RotationSpeed="1" BeforeSprite="0" ShowFlashes="0"><Position x="-107.622" y="190.495" z="0"/><Weapon></Weapon><PicturePosition x="58.6004" y="-132.4"/><WorldPosition x="18.8096" y="64.064" z="134.407"/></item><item Direction="90" Angle="142.504" SightMultiplier="1" Coverage="1" Ammo="100" GunPriority="1" RotationSpeed="1" BeforeSprite="0" ShowFlashes="0"><Position x="-108.329" y="157.261" z="0"/><Weapon></Weapon><PicturePosition x="34.6004" y="-126.4"/><WorldPosition x="4.66754" y="44.265" z="129.789"/></item><item Direction="90" Angle="142.504" SightMultiplier="1" Coverage="1" Ammo="100" GunPriority="1" RotationSpeed="1" BeforeSprite="0" ShowFlashes="0"><Position x="-108.329" y="114.835" z="0"/><Weapon></Weapon><PicturePosition x="4.60037" y="-114.4"/><WorldPosition x="-3.81781" y="10.3238" z="126.324"/></item><item Direction="90" Angle="142.504" SightMultiplier="1" Coverage="1" Ammo="100" GunPriority="1" RotationSpeed="1" BeforeSprite="0" ShowFlashes="0"><Position x="-104.793" y="73.1152" z="0"/><Weapon></Weapon><PicturePosition x="-22.3997" y="-98.4001"/><WorldPosition x="-32.8093" y="1.13141" z="99.7664"/></item><item Direction="270" Angle="142.504" SightMultiplier="1" Coverage="1" Ammo="100" GunPriority="1" RotationSpeed="1" BeforeSprite="1" ShowFlashes="0"><Position x="-68.7307" y="99.2781" z="0"/><Weapon></Weapon><PicturePosition x="21.6004" y="-84.4001"/><WorldPosition x="2.54608" y="28.0015" z="87.0648"/></item></FireSlots><Entrances><item Stormable="0"><Position x="16.1221" y="56.8518" z="0"/></item><item Stormable="0"><Position x="16.1221" y="169.989" z="0"/></item><item Stormable="0"><Position x="38.7496" y="147.361" z="0"/></item><item Stormable="0"><Position x="16.1221" y="34.2244" z="0"/></item><item Stormable="0"><Position x="16.1221" y="11.597" z="0"/></item></Entrances><FirePoints><item Direction="179.576" VerticalAngle="78"><Position x="-32.6683" y="8.06134" z="0"/><FireEffect>flamehouse1</FireEffect><PicturePosition x="-17.3995" y="-52.4001"/><WorldPosition x="-26.4454" y="1.83881" z="48.9595"/></item><item Direction="91.0051" VerticalAngle="78"><Position x="-82.1658" y="114.127" z="0"/><FireEffect>flamehouse1</FireEffect><PicturePosition x="22.6003" y="-84.4001"/><WorldPosition x="4.66754" y="27.2944" z="88.2194"/></item><item Direction="0" VerticalAngle="78"><Position x="-19.2333" y="182.717" z="0"/><FireEffect>flamehouse1</FireEffect><PicturePosition x="115.6" y="-86.4001"/><WorldPosition x="18.1019" y="145.381" z="47.8046"/></item><item Direction="254.745" VerticalAngle="78"><Position x="-27.0114" y="102.814" z="0"/><FireEffect>flamehouse1</FireEffect><PicturePosition x="53.6003" y="-89.4001"/><WorldPosition x="13.8597" y="61.9427" z="83.6005"/></item><item Direction="266.511" VerticalAngle="78"><Position x="22.486" y="131.098" z="0"/><FireEffect>flamehouse1</FireEffect><PicturePosition x="108.6" y="-56.4001"/><WorldPosition x="20.2231" y="133.361" z="18.9371"/></item></FirePoints><SmokePoints><item Direction="180" VerticalAngle="45"><Position x="-97.015" y="0.283142" z="0"/><FireEffect></FireEffect><PicturePosition x="-68.3995" y="-34.4001"/><WorldPosition x="-97.8632" y="1.1319" z="-0.69281"/></item><item Direction="180" VerticalAngle="45"><Position x="-51.7602" y="0.283142" z="0"/><FireEffect></FireEffect><PicturePosition x="-36.3997" y="-18.4001"/><WorldPosition x="-52.6086" y="1.13165" z="-0.692749"/></item><item Direction="180" VerticalAngle="45"><Position x="-6.50537" y="0.283142" z="0"/><FireEffect></FireEffect><PicturePosition x="-4.39975" y="-2.40012"/><WorldPosition x="-7.35358" y="1.13153" z="-0.692627"/></item><item Direction="270" VerticalAngle="45"><Position x="-5.09113" y="27.1532" z="0"/><FireEffect></FireEffect><PicturePosition x="15.6003" y="-11.4001"/><WorldPosition x="-4.52509" y="26.5875" z="0.461975"/></item><item Direction="270" VerticalAngle="45"><Position x="3.3941" y="58.2659" z="0"/><FireEffect></FireEffect><PicturePosition x="43.6004" y="-19.4001"/><WorldPosition x="-1.69684" y="63.3572" z="-4.15692"/></item><item Direction="270" VerticalAngle="45"><Position x="21.0718" y="95.7426" z="0"/><FireEffect></FireEffect><PicturePosition x="82.6004" y="-26.4001"/><WorldPosition x="20.2234" y="96.5912" z="-0.69281"/></item><item Direction="270" VerticalAngle="45"><Position x="21.0718" y="138.169" z="0"/><FireEffect></FireEffect><PicturePosition x="112.6" y="-41.4001"/><WorldPosition x="20.2232" y="139.017" z="-0.692932"/></item><item Direction="0" VerticalAngle="45"><Position x="4.80835" y="172.817" z="0"/><FireEffect></FireEffect><PicturePosition x="125.6" y="-59.4001"/><WorldPosition x="18.1017" y="159.524" z="10.8541"/></item><item Direction="0" VerticalAngle="45"><Position x="-29.1328" y="203.93" z="0"/><FireEffect></FireEffect><PicturePosition x="123.6" y="-82.4001"/><WorldPosition x="18.1019" y="156.695" z="38.567"/></item><item Direction="0" VerticalAngle="45"><Position x="-74.3876" y="203.93" z="0"/><FireEffect></FireEffect><PicturePosition x="91.6004" y="-98.4001"/><WorldPosition x="19.5165" y="110.026" z="76.6723"/></item><item Direction="90" VerticalAngle="45"><Position x="-108.329" y="192.616" z="0"/><FireEffect></FireEffect><PicturePosition x="59.6004" y="-106.4"/><WorldPosition x="19.5168" y="64.7712" z="104.385"/></item><item Direction="90" VerticalAngle="45"><Position x="-108.329" y="147.361" z="0"/><FireEffect></FireEffect><PicturePosition x="27.6004" y="-90.4001"/><WorldPosition x="3.96039" y="35.0726" z="91.6835"/></item><item Direction="90" VerticalAngle="45"><Position x="-108.329" y="102.107" z="0"/><FireEffect></FireEffect><PicturePosition x="-4.39957" y="-74.4001"/><WorldPosition x="-7.35321" y="1.13153" z="82.4459"/></item><item Direction="90" VerticalAngle="45"><Position x="-108.329" y="56.8517" z="0"/><FireEffect></FireEffect><PicturePosition x="-36.3996" y="-58.4001"/><WorldPosition x="-52.6082" y="1.13165" z="45.4953"/></item></SmokePoints><SmokeEffect>smokehouse1</SmokeEffect><DirExplosions><item Direction="180" VerticalAngle="78"><Position x="-89.2369" y="44.8309" z="0"/><PicturePosition x="-31.3995" y="-47.4001"/><WorldPosition x="-46.2442" y="1.83881" z="35.103"/></item><item Direction="270" VerticalAngle="78"><Position x="1.27283" y="126.855" z="0"/><PicturePosition x="90.6003" y="-44.4001"/><WorldPosition x="20.2234" y="107.905" z="15.473"/></item><item Direction="0" VerticalAngle="78"><Position x="-40.4465" y="203.93" z="0"/><PicturePosition x="115.6" y="-86.4001"/><WorldPosition x="18.1019" y="145.381" z="47.8046"/></item><item Direction="90" VerticalAngle="78"><Position x="-108.329" y="102.107" z="0"/><PicturePosition x="-4.39957" y="-74.4001"/><WorldPosition x="-7.35321" y="1.13153" z="82.4459"/></item><item Direction="225" VerticalAngle="78"><Position x="-40.4465" y="102.107" z="0"/><PicturePosition x="43.6003" y="-50.4001"/><WorldPosition x="-1.69672" y="63.357" z="31.6389"/></item></DirExplosions><DirExplosionEffect>expwall1</DirExplosionEffect><AmbientSound></AmbientSound></desc></base>
