<!-- edited with XML Spy v4.3 U (http://www.xmlspy.com) by Alexander Veselov (NIVAL Interactive) -->
<!-- deleted comment here -->
<!-- deleted comment here -->
<!--INTERMISSION INTERFACE: CHAPTER SCREEN (SELECT MISSION)-->
<!--PositionFlag: 0011 - left upper corner; 0012 - upper center; 0013 - right upper corner (X axis reversed); 0022 - center center; 0031 - left bottom corner (Y axis reversed); 0032 - center bottom; 0033 - right bottom (X axis reversed; Y axis reversed)-->
<!--TextAlign: aling of text, same flags as PositionFlag-->
<!--TextPos: spacing text; If TextAlign left, then x coord is left space of text. If TextAlign right, then x coord is right space of text. The same for top and bottom-->
<!--Background: 0 - no background is used (appearence*), 1 - background is used-->
<!--VisibleFlag: 0 - not visible, 1 - visible-->
<base Background="1">
	<States>
		<item EventID="-1">
			<AppearanceNormal Color="0xffffffff" Specular="0xff000000" Depth="0.0001">
				<SubRects>
					<item>
						<rect x1="0" y1="0" x2="1024" y2="768"/>
						<map x1="0" y1="0" x2="1024" y2="768"/>
					</item>
				</SubRects>
				<Texture>ui\intermissiontextures\back-chapter</Texture>
			</AppearanceNormal>
			<AppearanceHighlighted Color="0xffffffff" Specular="0xff000000" Depth="0.0001">
				<SubRects>
					<item>
						<rect x1="0" y1="0" x2="1024" y2="768"/>
						<map x1="0" y1="0" x2="1024" y2="768"/>
					</item>
				</SubRects>
				<Texture>ui\intermissiontextures\back-chapter</Texture>
			</AppearanceHighlighted>
			<AppearancePushed Color="0xffffffff" Specular="0xff000000" Depth="0.0001">
				<SubRects>
					<item>
						<rect x1="0" y1="0" x2="1024" y2="768"/>
						<map x1="0" y1="0" x2="1024" y2="768"/>
					</item>
				</SubRects>
				<Texture>ui\intermissiontextures\back-chapter</Texture>
			</AppearancePushed>
		</item>
	</States>
	<Script>ui\singlechapter</Script>
	<Children>
		<item ClassTypeID="0x10001105" ElementID="20000" PositionFlag="0x0011" TextAlign="0x0021" FontSize="2" TextColor="0xFFe29b00 " Background="0">
			<TextPos x="30" y="0"/>
			<ShadowShift x="1" y="2"/>
			<!--text: title [auto]-->
			<WindowPos x="30" y="30"/>
			<WindowSize x="850" y="70"/>
			<States>
				<item>
					<AppearanceNormal Color="-1" Specular="-16777216">
						<Texture/>
						<Maps x1="0" y1="768" x2="1000" y2="144"/>
					</AppearanceNormal>
					<AppearanceHighlighted Color="-1" Specular="-16777216">
						<Texture/>
						<Maps x1="0" y1="768" x2="1000" y2="144"/>
					</AppearanceHighlighted>
					<AppearancePushed Color="-1" Specular="-16777216">
						<Texture/>
						<Maps x1="0" y1="768" x2="1000" y2="144"/>
					</AppearancePushed>
					<PushSound/>
					<ClickSound/>
					<TextKey/>
				</item>
			</States>
		</item>
		<item ClassTypeID="0x10001105" ElementID="20001" PositionFlag="0x0011" TextAlign="0x0021" FontSize="1" TextColor="0xFFFDF2DB" Background="0">
			<TextPos x="30" y="15"/>
			<ShadowShift x="1" y="2"/>
			<!--text: header-description [static]-->
			<WindowPos x="30" y="134"/>
			<WindowSize x="410" y="30"/>
			<States>
				<item>
					<AppearanceNormal Color="-1" Specular="-16777216">
						<Texture/>
						<Maps x1="0" y1="768" x2="1000" y2="144"/>
					</AppearanceNormal>
					<AppearanceHighlighted Color="-1" Specular="-16777216">
						<Texture/>
						<Maps x1="0" y1="768" x2="1000" y2="144"/>
					</AppearanceHighlighted>
					<AppearancePushed Color="-1" Specular="-16777216">
						<Texture/>
						<Maps x1="0" y1="768" x2="1000" y2="144"/>
					</AppearancePushed>
					<PushSound/>
					<ClickSound/>
					<TextKey>imheader-mission-desc</TextKey>
				</item>
			</States>
		</item>
		<item ClassTypeID="0x10001105" ElementID="20002" PositionFlag="0x0011" TextAlign="0x0021" FontSize="1" TextColor="0xFFFDF2DB" Background="0">
			<TextPos x="30" y="15"/>
			<ShadowShift x="1" y="2"/>
			<!--text: header-map [static]-->
			<WindowPos x="528" y="134"/>
			<WindowSize x="410" y="30"/>
			<States>
				<item>
					<PushSound/>
					<ClickSound/>
					<TextKey>imheader-chapter-map</TextKey>
				</item>
			</States>
		</item>
		<item ClassTypeID="0x10001103" ElementID="10002" PositionFlag="0x0033" TextAlign="0x0022" FontSize="1" TextColor="0xFFFDF2DB">
			<TextPos x="-15" y="0"/>
			<ShiftText x="0" y="1"/>
			<ShadowShift x="1" y="2"/>
			<ToolTip>tt_ui_chapter_forward</ToolTip>
			<!--button: ==>-->
			<WindowPos x="176" y="30"/>
			<WindowSize x="132" y="62"/>
			<States>
				<item EventID="-1">
					<AppearanceNormal Color="0xffffffff" Specular="0xff000000" Depth="0.0001">
						<TileRects>
							<item>
								<rect x1="0" y1="0" x2="132" y2="62"/>
								<size x="132" y="62"/>
								<map x1="379" y1="2" x2="132" y2="62"/>
							</item>
							<item>
								<rect x1="19" y1="13" x2="82" y2="49"/>
								<size x="63" y="36"/>
								<map x1="189" y1="36" x2="63" y2="36"/>
							</item>
						</TileRects>
						<Texture>UI\IntermissionTextures\Buttons</Texture>
					</AppearanceNormal>
					<AppearanceHighlighted Color="0xffffffff" Specular="0xff000000" Depth="0.0001">
						<TileRects>
							<item>
								<rect x1="0" y1="0" x2="132" y2="62"/>
								<size x="132" y="62"/>
								<map x1="379" y1="2" x2="132" y2="62"/>
							</item>
							<item>
								<rect x1="19" y1="13" x2="82" y2="49"/>
								<size x="63" y="36"/>
								<map x1="189" y1="0" x2="63" y2="36"/>
							</item>
						</TileRects>
						<Texture>UI\IntermissionTextures\Buttons</Texture>
					</AppearanceHighlighted>
					<AppearancePushed Color="0xffffffff" Specular="0xff000000" Depth="0.0001">
						<TileRects>
							<item>
								<rect x1="0" y1="0" x2="132" y2="62"/>
								<size x="132" y="62"/>
								<map x1="379" y1="66" x2="132" y2="62"/>
							</item>
							<item>
								<rect x1="19" y1="13" x2="82" y2="49"/>
								<size x="63" y="36"/>
								<map x1="189" y1="36" x2="63" y2="36"/>
							</item>
						</TileRects>
						<Texture>UI\IntermissionTextures\Buttons</Texture>
					</AppearancePushed>
					<AppearanceDisabled Color="0xffffffff" Specular="0xff000000" Depth="0.0001">
						<TileRects>
							<item>
								<rect x1="0" y1="0" x2="132" y2="62"/>
								<size x="132" y="62"/>
								<map x1="379" y1="2" x2="132" y2="62"/>
							</item>
							<item>
								<rect x1="19" y1="13" x2="82" y2="49"/>
								<size x="63" y="36"/>
								<map x1="189" y1="72" x2="63" y2="36"/>
							</item>
						</TileRects>
						<Texture>UI\IntermissionTextures\Buttons</Texture>
					</AppearanceDisabled>
					<PushSound>sounds\buttons\select</PushSound>
					<ClickSound>sounds\buttons\ok</ClickSound>
				</item>
			</States>
		</item>
		<item ClassTypeID="0x10001103" ElementID="10001" PositionFlag="0x0033" TextAlign="0x0022" FontSize="1" TextColor="0xFFFDF2DB">
			<TextPos x="-15" y="0"/>
			<ShiftText x="0" y="1"/>
			<ShadowShift x="1" y="2"/>
			<ToolTip>tt_ui_chapter_backward</ToolTip>
			<!--button: <==-->
			<WindowPos x="42" y="30"/>
			<WindowSize x="132" y="62"/>
			<States>
				<item EventID="-1">
					<AppearanceNormal Color="0xffffffff" Specular="0xff000000" Depth="0.0001">
						<TileRects>
							<item>
								<rect x1="0" y1="0" x2="132" y2="62"/>
								<size x="132" y="62"/>
								<map x1="379" y1="2" x2="132" y2="62"/>
							</item>
							<item>
								<rect x1="19" y1="13" x2="82" y2="49"/>
								<size x="63" y="36"/>
								<map x1="126" y1="36" x2="63" y2="36"/>
							</item>
						</TileRects>
						<Texture>UI\IntermissionTextures\Buttons</Texture>
					</AppearanceNormal>
					<AppearanceHighlighted Color="0xffffffff" Specular="0xff000000" Depth="0.0001">
						<TileRects>
							<item>
								<rect x1="0" y1="0" x2="132" y2="62"/>
								<size x="132" y="62"/>
								<map x1="379" y1="2" x2="132" y2="62"/>
							</item>
							<item>
								<rect x1="19" y1="13" x2="82" y2="49"/>
								<size x="63" y="36"/>
								<map x1="126" y1="0" x2="63" y2="36"/>
							</item>
						</TileRects>
						<Texture>UI\IntermissionTextures\Buttons</Texture>
					</AppearanceHighlighted>
					<AppearancePushed Color="0xffffffff" Specular="0xff000000" Depth="0.0001">
						<TileRects>
							<item>
								<rect x1="0" y1="0" x2="132" y2="62"/>
								<size x="132" y="62"/>
								<map x1="379" y1="66" x2="132" y2="62"/>
							</item>
							<item>
								<rect x1="19" y1="13" x2="82" y2="49"/>
								<size x="63" y="36"/>
								<map x1="126" y1="36" x2="63" y2="36"/>
							</item>
						</TileRects>
						<Texture>UI\IntermissionTextures\Buttons</Texture>
					</AppearancePushed>
					<AppearanceDisabled Color="0xffffffff" Specular="0xff000000" Depth="0.0001">
						<TileRects>
							<item>
								<rect x1="0" y1="0" x2="132" y2="62"/>
								<size x="132" y="62"/>
								<map x1="379" y1="2" x2="132" y2="62"/>
							</item>
							<item>
								<rect x1="19" y1="13" x2="82" y2="49"/>
								<size x="63" y="36"/>
								<map x1="126" y1="72" x2="63" y2="36"/>
							</item>
						</TileRects>
						<Texture>UI\IntermissionTextures\Buttons</Texture>
					</AppearanceDisabled>
					<PushSound>sounds\buttons\select</PushSound>
					<ClickSound>sounds\buttons\ok</ClickSound>
				</item>
			</States>
		</item>
		<item ClassTypeID="0x10001103" ElementID="10004" PositionFlag="0x0031" TextAlign="0x0022" FontSize="1">
			<TextPos x="-15" y="0"/>
			<ShiftText x="0" y="1"/>
			<ShadowShift x="1" y="2"/>
			<ToolTip>tt_ui_chapter_player</ToolTip>
			<!--button: player-->
			<WindowPos x="40" y="30"/>
			<WindowSize x="132" y="62"/>
			<States>
				<item EventID="-1">
					<AppearanceNormal Color="0xffffffff" Specular="0xff000000" Depth="0.0001">
						<TileRects>
							<item>
								<rect x1="0" y1="0" x2="132" y2="62"/>
								<size x="132" y="62"/>
								<map x1="379" y1="2" x2="132" y2="62"/>
							</item>
							<item>
								<rect x1="19" y1="13" x2="82" y2="49"/>
								<size x="63" y="36"/>
								<map x1="252" y1="144" x2="63" y2="36"/>
							</item>
						</TileRects>
						<Texture>UI\IntermissionTextures\Buttons</Texture>
					</AppearanceNormal>
					<AppearanceHighlighted Color="0xffffffff" Specular="0xff000000" Depth="0.0001">
						<TileRects>
							<item>
								<rect x1="0" y1="0" x2="132" y2="62"/>
								<size x="132" y="62"/>
								<map x1="379" y1="2" x2="132" y2="62"/>
							</item>
							<item>
								<rect x1="19" y1="13" x2="82" y2="49"/>
								<size x="63" y="36"/>
								<map x1="252" y1="108" x2="63" y2="36"/>
							</item>
						</TileRects>
						<Texture>UI\IntermissionTextures\Buttons</Texture>
					</AppearanceHighlighted>
					<AppearancePushed Color="0xffffffff" Specular="0xff000000" Depth="0.0001">
						<TileRects>
							<item>
								<rect x1="0" y1="0" x2="132" y2="62"/>
								<size x="132" y="62"/>
								<map x1="379" y1="66" x2="132" y2="62"/>
							</item>
							<item>
								<rect x1="19" y1="13" x2="82" y2="49"/>
								<size x="63" y="36"/>
								<map x1="252" y1="144" x2="63" y2="36"/>
							</item>
						</TileRects>
						<Texture>UI\IntermissionTextures\Buttons</Texture>
					</AppearancePushed>
					<AppearanceDisabled Color="0xffffffff" Specular="0xff000000" Depth="0.0001">
						<TileRects>
							<item>
								<rect x1="0" y1="0" x2="132" y2="62"/>
								<size x="132" y="62"/>
								<map x1="379" y1="2" x2="132" y2="62"/>
							</item>
							<item>
								<rect x1="19" y1="13" x2="82" y2="49"/>
								<size x="63" y="36"/>
								<map x1="252" y1="180" x2="63" y2="36"/>
							</item>
						</TileRects>
						<Texture>UI\IntermissionTextures\Buttons</Texture>
					</AppearanceDisabled>
					<PushSound>sounds\buttons\select</PushSound>
					<ClickSound>sounds\buttons\ok</ClickSound>
				</item>
			</States>
		</item>
		<item ClassTypeID="0x10001103" ElementID="10003" PositionFlag="0x0031" TextAlign="0x0022" FontSize="1" TextColor="0xFFFDF2DB" VisibleFlag="0">
			<TextPos x="-15" y="0"/>
			<ShiftText x="0" y="1"/>
			<ShadowShift x="1" y="2"/>
			<ToolTip>tt_ui_chapter_unitlist</ToolTip>
			<!--button: units-->
			<WindowPos x="175" y="30"/>
			<WindowSize x="132" y="62"/>
			<States>
				<item EventID="-1">
					<AppearanceNormal Color="0xffffffff" Specular="0xff000000" Depth="0.0001">
						<TileRects>
							<item>
								<rect x1="0" y1="0" x2="132" y2="62"/>
								<size x="132" y="62"/>
								<map x1="379" y1="2" x2="132" y2="62"/>
							</item>
							<item>
								<rect x1="19" y1="13" x2="82" y2="49"/>
								<size x="63" y="36"/>
								<map x1="63" y1="36" x2="63" y2="36"/>
							</item>
						</TileRects>
						<Texture>UI\IntermissionTextures\Buttons</Texture>
					</AppearanceNormal>
					<AppearanceHighlighted Color="0xffffffff" Specular="0xff000000" Depth="0.0001">
						<TileRects>
							<item>
								<rect x1="0" y1="0" x2="132" y2="62"/>
								<size x="132" y="62"/>
								<map x1="379" y1="2" x2="132" y2="62"/>
							</item>
							<item>
								<rect x1="19" y1="13" x2="82" y2="49"/>
								<size x="63" y="36"/>
								<map x1="63" y1="0" x2="63" y2="36"/>
							</item>
						</TileRects>
						<Texture>UI\IntermissionTextures\Buttons</Texture>
					</AppearanceHighlighted>
					<AppearancePushed Color="0xffffffff" Specular="0xff000000" Depth="0.0001">
						<TileRects>
							<item>
								<rect x1="0" y1="0" x2="132" y2="62"/>
								<size x="132" y="62"/>
								<map x1="379" y1="66" x2="132" y2="62"/>
							</item>
							<item>
								<rect x1="19" y1="13" x2="82" y2="49"/>
								<size x="63" y="36"/>
								<map x1="63" y1="36" x2="63" y2="36"/>
							</item>
						</TileRects>
						<Texture>UI\IntermissionTextures\Buttons</Texture>
					</AppearancePushed>
					<AppearanceDisabled Color="0xffffffff" Specular="0xff000000" Depth="0.0001">
						<TileRects>
							<item>
								<rect x1="0" y1="0" x2="132" y2="62"/>
								<size x="132" y="62"/>
								<map x1="379" y1="2" x2="132" y2="62"/>
							</item>
							<item>
								<rect x1="19" y1="13" x2="82" y2="49"/>
								<size x="63" y="36"/>
								<map x1="63" y1="72" x2="63" y2="36"/>
							</item>
						</TileRects>
						<Texture>UI\IntermissionTextures\Buttons</Texture>
					</AppearanceDisabled>
					<PushSound>sounds\buttons\select</PushSound>
					<ClickSound>sounds\buttons\ok</ClickSound>
				</item>
			</States>
		</item>
		<item ClassTypeID="0x10001103" ElementID="10005" PositionFlag="0x0031" TextAlign="0x0022" FontSize="1" TextColor="0xFFFDF2DB">
			<!--button: SAVE GAME-->
			<TextPos x="-15" y="0"/>
			<ShiftText x="0" y="1"/>
			<ShadowShift x="1" y="2"/>
			<ToolTip>tt_ui_campain_save_game</ToolTip>
			<WindowPos x="310" y="30"/>
			<WindowSize x="132" y="62"/>
			<States>
				<item EventID="-1">
					<AppearanceNormal Color="0xffffffff" Specular="0xff000000" Depth="0.0001">
						<TileRects>
							<item>
								<rect x1="0" y1="0" x2="132" y2="62"/>
								<size x="132" y="62"/>
								<map x1="379" y1="2" x2="132" y2="62"/>
							</item>
							<item>
								<rect x1="19" y1="13" x2="82" y2="49"/>
								<size x="63" y="36"/>
								<map x1="0" y1="252" x2="63" y2="36"/>
							</item>
						</TileRects>
						<Texture>UI\IntermissionTextures\Buttons</Texture>
					</AppearanceNormal>
					<AppearanceHighlighted Color="0xffffffff" Specular="0xff000000" Depth="0.0001">
						<TileRects>
							<item>
								<rect x1="0" y1="0" x2="132" y2="62"/>
								<size x="132" y="62"/>
								<map x1="379" y1="2" x2="132" y2="62"/>
							</item>
							<item>
								<rect x1="19" y1="13" x2="82" y2="49"/>
								<size x="63" y="36"/>
								<map x1="0" y1="216" x2="63" y2="36"/>
							</item>
						</TileRects>
						<Texture>UI\IntermissionTextures\Buttons</Texture>
					</AppearanceHighlighted>
					<AppearancePushed Color="0xffffffff" Specular="0xff000000" Depth="0.0001">
						<TileRects>
							<item>
								<rect x1="0" y1="0" x2="132" y2="62"/>
								<size x="132" y="62"/>
								<map x1="379" y1="66" x2="132" y2="62"/>
							</item>
							<item>
								<rect x1="19" y1="13" x2="82" y2="49"/>
								<size x="63" y="36"/>
								<map x1="0" y1="252" x2="63" y2="36"/>
							</item>
						</TileRects>
						<Texture>UI\IntermissionTextures\Buttons</Texture>
					</AppearancePushed>
					<AppearanceDisabled Color="0xffffffff" Specular="0xff000000" Depth="0.0001">
						<TileRects>
							<item>
								<rect x1="0" y1="0" x2="132" y2="62"/>
								<size x="132" y="62"/>
								<map x1="379" y1="2" x2="132" y2="62"/>
							</item>
							<item>
								<rect x1="19" y1="13" x2="82" y2="49"/>
								<size x="63" y="36"/>
								<map x1="0" y1="288" x2="63" y2="36"/>
							</item>
						</TileRects>
						<Texture>UI\IntermissionTextures\Buttons</Texture>
					</AppearanceDisabled>
					<PushSound>sounds\buttons\select</PushSound>
					<ClickSound>sounds\buttons\ok</ClickSound>
				</item>
			</States>
		</item>
		<item ClassTypeID="0x10001103" ElementID="10006" PositionFlag="0x0031" TextAlign="0x0022" FontSize="1" TextColor="0xFFFDF2DB">
			<TextPos x="-15" y="0"/>
			<ShiftText x="0" y="1"/>
			<ShadowShift x="1" y="2"/>
			<ToolTip>Textes\UI\Intermission\Upgrades\tt_button_warehouse</ToolTip>
			<!--button: warehouse-->
			<WindowPos x="175" y="30"/>
			<WindowSize x="132" y="62"/>
			<States>
				<item EventID="-1">
					<AppearanceNormal Color="0xffffffff" Specular="0xff000000" Depth="0.0001">
						<TileRects>
							<item>
								<rect x1="0" y1="0" x2="132" y2="62"/>
								<size x="132" y="62"/>
								<map x1="379" y1="2" x2="132" y2="62"/>
							</item>
							<item>
								<rect x1="19" y1="13" x2="82" y2="49"/>
								<size x="63" y="36"/>
								<map x1="63" y1="144" x2="63" y2="36"/>
							</item>
						</TileRects>
						<Texture>UI\IntermissionTextures\Buttons</Texture>
					</AppearanceNormal>
					<AppearanceHighlighted Color="0xffffffff" Specular="0xff000000" Depth="0.0001">
						<TileRects>
							<item>
								<rect x1="0" y1="0" x2="132" y2="62"/>
								<size x="132" y="62"/>
								<map x1="379" y1="2" x2="132" y2="62"/>
							</item>
							<item>
								<rect x1="19" y1="13" x2="82" y2="49"/>
								<size x="63" y="36"/>
								<map x1="63" y1="108" x2="63" y2="36"/>
							</item>
						</TileRects>
						<Texture>UI\IntermissionTextures\Buttons</Texture>
					</AppearanceHighlighted>
					<AppearancePushed Color="0xffffffff" Specular="0xff000000" Depth="0.0001">
						<TileRects>
							<item>
								<rect x1="0" y1="0" x2="132" y2="62"/>
								<size x="132" y="62"/>
								<map x1="379" y1="66" x2="132" y2="62"/>
							</item>
							<item>
								<rect x1="19" y1="13" x2="82" y2="49"/>
								<size x="63" y="36"/>
								<map x1="63" y1="144" x2="63" y2="36"/>
							</item>
						</TileRects>
						<Texture>UI\IntermissionTextures\Buttons</Texture>
					</AppearancePushed>
					<AppearanceDisabled Color="0xffffffff" Specular="0xff000000" Depth="0.0001">
						<TileRects>
							<item>
								<rect x1="0" y1="0" x2="132" y2="62"/>
								<size x="132" y="62"/>
								<map x1="379" y1="2" x2="132" y2="62"/>
							</item>
							<item>
								<rect x1="19" y1="13" x2="82" y2="49"/>
								<size x="63" y="36"/>
								<map x1="63" y1="180" x2="63" y2="36"/>
							</item>
						</TileRects>
						<Texture>UI\IntermissionTextures\Buttons</Texture>
					</AppearanceDisabled>
					<PushSound>sounds\buttons\select</PushSound>
					<ClickSound>sounds\buttons\ok</ClickSound>
				</item>
			</States>
		</item>
		<item ClassTypeID="0x10001103" ElementID="10009" PositionFlag="0x0031" TextAlign="0x0022" FontSize="1" TextColor="0xFFFDF2DB" VisibleFlag="0" ActiveFlag="0">
			<TextPos x="-15" y="0"/>
			<ShiftText x="0" y="1"/>
			<ShadowShift x="1" y="2"/>
			<ToolTip>tt_ui_chapter_stats</ToolTip>
			<!--button: stats-->
			<WindowPos x="310" y="30"/>
			<WindowSize x="132" y="62"/>
			<States>
				<item EventID="-1">
					<AppearanceNormal Color="0xffffffff" Specular="0xff000000" Depth="0.0001">
						<TileRects>
							<item>
								<rect x1="0" y1="0" x2="132" y2="62"/>
								<size x="132" y="62"/>
								<map x1="379" y1="2" x2="132" y2="62"/>
							</item>
							<item>
								<rect x1="19" y1="13" x2="82" y2="49"/>
								<size x="63" y="36"/>
								<map x1="252" y1="36" x2="63" y2="36"/>
							</item>
						</TileRects>
						<Texture>UI\IntermissionTextures\Buttons</Texture>
					</AppearanceNormal>
					<AppearanceHighlighted Color="0xffffffff" Specular="0xff000000" Depth="0.0001">
						<TileRects>
							<item>
								<rect x1="0" y1="0" x2="132" y2="62"/>
								<size x="132" y="62"/>
								<map x1="379" y1="2" x2="132" y2="62"/>
							</item>
							<item>
								<rect x1="19" y1="13" x2="82" y2="49"/>
								<size x="63" y="36"/>
								<map x1="252" y1="0" x2="63" y2="36"/>
							</item>
						</TileRects>
						<Texture>UI\IntermissionTextures\Buttons</Texture>
					</AppearanceHighlighted>
					<AppearancePushed Color="0xffffffff" Specular="0xff000000" Depth="0.0001">
						<TileRects>
							<item>
								<rect x1="0" y1="0" x2="132" y2="62"/>
								<size x="132" y="62"/>
								<map x1="379" y1="66" x2="132" y2="62"/>
							</item>
							<item>
								<rect x1="19" y1="13" x2="82" y2="49"/>
								<size x="63" y="36"/>
								<map x1="252" y1="36" x2="63" y2="36"/>
							</item>
						</TileRects>
						<Texture>UI\IntermissionTextures\Buttons</Texture>
					</AppearancePushed>
					<AppearanceDisabled Color="0xffffffff" Specular="0xff000000" Depth="0.0001">
						<TileRects>
							<item>
								<rect x1="0" y1="0" x2="132" y2="62"/>
								<size x="132" y="62"/>
								<map x1="379" y1="2" x2="132" y2="62"/>
							</item>
							<item>
								<rect x1="19" y1="13" x2="82" y2="49"/>
								<size x="63" y="36"/>
								<map x1="252" y1="72" x2="63" y2="36"/>
							</item>
						</TileRects>
						<Texture>UI\IntermissionTextures\Buttons</Texture>
					</AppearanceDisabled>
					<PushSound>sounds\buttons\select</PushSound>
					<ClickSound>sounds\buttons\ok</ClickSound>
				</item>
			</States>
		</item>
		<item ClassTypeID="0x1000111c" ElementID="2000" PositionFlag="0x0011" TextColor="0xff000000" Background="0" VisibleFlag="1" LeftSpace="20" RightSpace="20" TopSpace="71" BottomSpace="15" RedLine="1" VSubSpace="5">
			<Children>
				<item ClassTypeID="0x10001109" ElementID="1" CurrentState="0" PositionFlag="0x0013" ButtonStep="15">
					<Children>
						<item ClassTypeID="0x10001103" ElementID="1" CurrentState="0" PositionFlag="0x0031">
							<!--scrollbar upper button-->
							<WindowSize x="45" y="58"/>
							<States>
								<item EventID="-1">
									<AppearanceNormal Color="0xffffffff" Specular="0xff000000">
										<Maps x1="636" y1="769" x2="45" y2="58"/>
										<Texture>ui\IntermissionTextures\back-chapter</Texture>
									</AppearanceNormal>
									<AppearanceHighlighted Color="0xffffffff" Specular="0xff000000">
										<Maps x1="636" y1="769" x2="45" y2="58"/>
										<Texture>ui\IntermissionTextures\back-chapter</Texture>
									</AppearanceHighlighted>
									<AppearancePushed Color="0xffffffff" Specular="0xff000000">
										<Maps x1="636" y1="827" x2="45" y2="58"/>
										<Texture>ui\IntermissionTextures\back-chapter</Texture>
									</AppearancePushed>
								</item>
							</States>
						</item>
						<item ClassTypeID="0x10001103" ElementID="2" CurrentState="0" PositionFlag="0x0031">
							<!--scrollbar lower button-->
							<WindowSize x="45" y="58"/>
							<States>
								<item EventID="-1">
									<AppearanceNormal Color="0xffffffff" Specular="0xff000000">
										<Maps x1="591" y1="769" x2="45" y2="58"/>
										<Texture>ui\IntermissionTextures\back-chapter</Texture>
									</AppearanceNormal>
									<AppearanceHighlighted Color="0xffffffff" Specular="0xff000000">
										<Maps x1="591" y1="769" x2="45" y2="58"/>
										<Texture>ui\IntermissionTextures\back-chapter</Texture>
									</AppearanceHighlighted>
									<AppearancePushed Color="0xffffffff" Specular="0xff000000">
										<Maps x1="591" y1="827" x2="45" y2="58"/>
										<Texture>ui\IntermissionTextures\back-chapter</Texture>
									</AppearancePushed>
								</item>
							</States>
						</item>
						<item ClassTypeID="0x10001108" ElementID="3" CurrentState="0" PositionFlag="0x0031" Min="0" Max="20" Step="1" Position="0" Width="41" Vertical="1" Elevator_Width="33">
							<Elevator_Texture>ui\IntermissionTextures\back-chapter</Elevator_Texture>
							<Elevator_Maps x1="681" y1="783" x2="45" y2="33"/>
							<!--slider. elevator - button on scrollbar. states - elevator background. elevator_width - how long elevator is along scrollbar; elevator maps - texture of elevator-->
							<WindowSize x="41" y="0"/>
							<States>
								<item EventID="-1">
									<AppearanceNormal Color="0xffffffff" Specular="0xff000000">
										<Placement Flags="0x1111">
											<Pos x="100" y="100"/>
											<Size x="64" y="32"/>
										</Placement>
										<Maps x1="108" y1="0" x2="40" y2="33"/>
										<Texture>ui\slider</Texture>
									</AppearanceNormal>
									<AppearanceHighlighted Color="0xffffffff" Specular="0xff000000">
										<Placement Flags="0x1111">
											<Pos x="100" y="100"/>
											<Size x="64" y="32"/>
										</Placement>
										<Maps x1="108" y1="0" x2="27" y2="128"/>
										<Texture>ui\slider</Texture>
									</AppearanceHighlighted>
									<AppearancePushed Color="0xffffffff" Specular="0xff000000">
										<Placement Flags="0x1111">
											<Pos x="100" y="100"/>
											<Size x="64" y="32"/>
										</Placement>
										<Maps x1="108" y1="0" x2="27" y2="128"/>
										<Texture>ui\slider</Texture>
									</AppearancePushed>
								</item>
							</States>
						</item>
					</Children>
					<WindowPos x="0" y="0"/>
					<WindowSize x="45" y="0"/>
				</item>
				<item ClassTypeID="0x10001107" ElementID="5" PositionFlag="0x0011">
					<WindowPos x="0" y="0"/>
					<WindowSize x="417" y="0"/>
				</item>
			</Children>
			<!--scroll: chapter text [auto]-->
			<WindowPos x="38" y="130"/>
			<WindowSize x="462" y="511"/>
			<States>
				<item EventID="-1">
					<AppearanceNormal Color="0xffffffff" Specular="0xff000000" Depth="0.0001">
						<Placement Flags="0x1111">
							<Pos x="200" y="100"/>
							<Size x="64" y="32"/>
						</Placement>
					</AppearanceNormal>
					<AppearanceHighlighted Color="0xffffffff" Specular="0xff000000" Depth="0.0001">
						<Placement Flags="0x1111">
							<Pos x="200" y="100"/>
							<Size x="64" y="32"/>
						</Placement>
					</AppearanceHighlighted>
					<AppearancePushed Color="0xffffffff" Specular="0xff000000" Depth="0.0001">
						<Placement Flags="0x1111">
							<Pos x="200" y="100"/>
							<Size x="64" y="32"/>
						</Placement>
					</AppearancePushed>
				</item>
			</States>
		</item>
		<item ClassTypeID="0x10001107" ElementID="100" PositionFlag="0x0011" Background="1">
			<Children/>
			<Script>ui\common\campainselect</Script>
			<!--picture: chapter map [auto]-->
			<WindowPos x="556" y="200"/>
			<WindowSize x="-1" y="-1"/>
			<States>
				<item EventID="-1">
					<AppearanceNormal Color="0xffffffff" Specular="0xff000000" Depth="0.0001">
						<Maps x1="0" y1="0" x2="492" y2="638"/>
						<Texture>ui\maps</Texture>
					</AppearanceNormal>
					<AppearanceHighlighted Color="0xffffffff" Specular="0xff000000" Depth="0.0001">
						<Maps x1="493" y1="0" x2="492" y2="638"/>
						<Texture>ui\maps</Texture>
					</AppearanceHighlighted>
					<AppearancePushed Color="0xffffffff" Specular="0xff000000" Depth="0.0001">
						<Maps x1="493" y1="0" x2="492" y2="638"/>
						<Texture>ui\maps</Texture>
					</AppearancePushed>
				</item>
			</States>
		</item>
		<item ClassTypeID="0x10001103" PositionFlag="0x0013" VisibleFlag="1" ActiveFlag="1" Background="1" ElementID="31416">
			<!--tutorial BUTTON-->
			<ToolTip>tt_ui_intermission_help_button</ToolTip>
			<WindowPos x="41" y="37"/>
			<WindowSize x="76" y="59"/>
			<States>
				<item>
					<AppearanceNormal Color="-1" Specular="-16777216">
						<Maps x1="0" y1="383" x2="76" y2="59"/>
						<Texture>UI\IntermissionTextures\Buttons</Texture>
					</AppearanceNormal>
					<AppearanceHighlighted Color="-1" Specular="-16777216">
						<Texture>UI\IntermissionTextures\Buttons</Texture>
						<Maps x1="0" y1="324" x2="76" y2="59"/>
					</AppearanceHighlighted>
					<AppearancePushed Color="-1" Specular="-16777216">
						<Texture>UI\IntermissionTextures\Buttons</Texture>
						<Maps x1="0" y1="442" x2="76" y2="59"/>
					</AppearancePushed>
					<PushSound>sounds\buttons\select</PushSound>
					<ClickSound>sounds\buttons\ok</ClickSound>
				</item>
			</States>
		</item>
		<item ClassTypeID="0x10001105" ElementID="31415" PositionFlag="0x0022" Background="0" VisibleFlag="0">
			<Script>ui\imtutorial</Script>
			<!--inter mission tutorial-->
			<WindowPos x="0" y="0"/>
			<WindowSize x="576" y="420"/>
			<States>
				<item>
					<TextKey>textes\imtutorial\chapter</TextKey>
				</item>
			</States>
		</item>
	</Children>
</base>
